[{"_data":{"<Age>k__BackingField":25,"<Name>k__BackingField":"Noah"},"_fieldsCount":2,"_fildNames":["<Name>k__BackingField","<Age>k__BackingField"],"_fildTypes":["System.String","System.Int32"]},{"_data":{"<Age>k__BackingField":27,"<Name>k__BackingField":"Liam"},"_fieldsCount":2,"_fildNames":["<Name>k__BackingField","<Age>k__BackingField"],"_fildTypes":["System.String","System.Int32"]},{"_data":{"<Age>k__BackingField":30,"<Name>k__BackingField":"Jacob"},"_fieldsCount":2,"_fildNames":["<Name>k__BackingField","<Age>k__BackingField"],"_fildTypes":["System.String","System.Int32"]}]